<databaseChangeLog xmlns:xsi="http://www.w3.org/2001/XMLSchema-instance"
                   xmlns="http://www.liquibase.org/xml/ns/dbchangelog"
                   xsi:schemaLocation="http://www.liquibase.org/xml/ns/dbchangelog
                                       http://www.liquibase.org/xml/ns/dbchangelog/dbchangelog-3.6.xsd">
    <changeSet id="1809130926_01" author="akorchaginn" runOnChange="true" dbms="postgresql">
        <preConditions onFail="MARK_RAN">
            <tableExists tableName="employee"/>
        </preConditions>
        
        <addColumn tableName="employee">
            <column>position</column>
        </addColumn>

        <addColumn tableName="employee">
            <column>unit</column>
        </addColumn>

        <addColumn tableName="employee">
            <column>period</column>
        </addColumn>
    </changeSet>
    
</databaseChangeLog>
